src/register_file.vhd
library ieee;
use ieee.std_logic_1164.all;
use ieee.numeric_std.all;

entity register_file is
  port (
    clk   : in std_logic;
    rst   : in std_logic;
    RdWEn : in std_logic;
    Ra    : in std_logic_vector(3 downto 0);
    Rb    : in std_logic_vector(3 downto 0);
    Rd    : in std_logic_vector(3 downto 0);
    Res   : in std_logic_vector(15 downto 0);
    SRCa  : out std_logic_vector(15 downto 0);
    SRCb  : out std_logic_vector(15 downto 0)
  );
end entity;

architecture behave of register_file is
  type reg_array is array(0 to 15) of std_logic_vector(15 downto 0);
  signal registers : reg_array := (others => (others => '0'));

begin
  process (clk, rst)
  begin
    if rst = '1' then
      registers <= (others => (others => '0'));
    elsif rising_edge(clk) then
      if RdWEn = '1' then
        registers(to_integer(unsigned(Rd))) <= RES;
      end if;
    end if;
  end process;

  SRCa <= registers(to_integer(unsigned(Ra)));
  SRCb <= registers(to_integer(unsigned(Rb)));
end behave;

tb/register_file_tb.vhd
library ieee;
use ieee.std_logic_1164.all;
use ieee.numeric_std.all;
entity tb_register_file is
end entity;

architecture test of tb_register_file is
  signal clk        : std_logic                     := '0';
  signal rst        : std_logic                     := '0';
  signal RdWEn      : std_logic                     := '0';
  signal Ra, Rb, Rd : std_logic_vector(3 downto 0)  := (others => '0');
  signal Res        : std_logic_vector(15 downto 0) := (others => '0');
  signal SRCa, SRCb : std_logic_vector(15 downto 0);

  constant clk_period : time := 10 ns;
  constant sim_period : time := 200 ns;

  signal sim_done : boolean := false;

begin
  UUT : entity work.register_file
    port map
    (
      clk   => clk,
      rst   => rst,
      RdWEn => RdWEn,
      Ra    => Ra,
      Rb    => Rb,
      Rd    => Rd,
      Res   => Res,
      SRCa  => SRCa,
      SRCb  => SRCb
    );

  clk_process : process
  begin
    while not sim_done loop
      clk <= '0';
      wait for clk_period/2;
      clk <= '1';
      wait for clk_period/2;
    end loop;
  end process;
  sim_proc : process
  begin
    rst <= '1';
    wait for clk_period;
    rst <= '0';
    wait for clk_period;

    Ra <= "0100";
    Rb <= "1011";

    wait for 2 ns;
    assert(SRCa = x"0000" and SRCb = x"0000")
    report"Error" severity error;

    RdWEn <= '1';
    Rd    <= "1011";
    Res   <= x"AAAA";
    wait for clk_period;
    RdWEn <= '0';
    Rd    <= "0001";
    Res   <= x"A111";
    wait for clk_period;

    Ra <= "1011";
    Rb <= "0001";
    wait for 2 ns;
    assert(SRCa = x"AAAA" and SRCb = x"0000")
    report"Error" severity error;
    rst <= '1';
    wait for clk_period;

    rst <= '0';
    wait for clk_period;

    assert(SRCa = x"0000")
    report"Error" severity error;
    sim_done <= true;
    wait;
  end process;
end architecture;

waveforms/file_register_wave.vcd
$date
  Fri Apr 24 04:43:45 2026
$end
$version
  GHDL v0
$end
$timescale
  1 fs
$end
$scope module standard $end
$upscope $end
$scope module std_logic_1164 $end
$upscope $end
$scope module numeric_std $end
$upscope $end
$scope module tb_register_file $end
$var reg 1 ! clk $end
$var reg 1 " rst $end
$var reg 1 # rdwen $end
$var reg 4 $ ra[3:0] $end
$var reg 4 % rb[3:0] $end
$var reg 4 & rd[3:0] $end
$var reg 16 ' res[15:0] $end
$var reg 16 ( srca[15:0] $end
$var reg 16 ) srcb[15:0] $end
$var reg 1 * sim_done $end
$scope module uut $end
$var reg 1 + clk $end
$var reg 1 , rst $end
$var reg 1 - rdwen $end
$var reg 4 . ra[3:0] $end
$var reg 4 / rb[3:0] $end
$var reg 4 0 rd[3:0] $end
$var reg 16 1 res[15:0] $end
$var reg 16 2 srca[15:0] $end
$var reg 16 3 srcb[15:0] $end
$comment registers is not handled $end
$upscope $end
$upscope $end
$enddefinitions $end
#0
0!
1"
0#
b0000 $
b0000 %
b0000 &
b0000000000000000 '
b0000000000000000 (
b0000000000000000 )
0*
0+
1,
0-
b0000 .
b0000 /
b0000 0
b0000000000000000 1
b0000000000000000 2
b0000000000000000 3
#5000000
1!
1+
#10000000
0!
0"
0+
0,
#15000000
1!
1+
#20000000
0!
b0100 $
b1011 %
0+
b0100 .
b1011 /
#22000000
1#
b1011 &
b1010101010101010 '
1-
b1011 0
b1010101010101010 1
#25000000
1!
b1010101010101010 )
1+
b1010101010101010 3
#30000000
0!
0+
#32000000
0#
b0001 &
b1010000100010001 '
0-
b0001 0
b1010000100010001 1
#35000000
1!
1+
#40000000
0!
0+
#42000000
b1011 $
b0001 %
b1010101010101010 (
b0000000000000000 )
b1011 .
b0001 /
b1010101010101010 2
b0000000000000000 3
#44000000
1"
b0000000000000000 (
1,
b0000000000000000 2
#45000000
1!
1+
#50000000
0!
0+
#54000000
0"
0,
#55000000
1!
1+
#60000000
0!
0+
#64000000
1*
